profile_instagram_local/__init__.py
profile_instagram_local/constants_instagram_graphql.py
profile_instagram_local/instagram_api.py
profile_instagram_local/instagram_profile.py
profile_instagram_local/utils.py
profile_instagram_local-0.0.16.dist-info/METADATA
profile_instagram_local-0.0.16.dist-info/WHEEL
profile_instagram_local-0.0.16.dist-info/top_level.txt
profile_instagram_local-0.0.16.dist-info/RECORD
