Metadata-Version: 2.1
Name: profile-instagram-local
Version: 0.0.16
Summary: PyPI Package for Circles profile-instagram-graphql-imp-local-python-package Local Python
Home-page: https://github.com/circles
Author: Circles
Author-email: info@circles.life
Classifier: Programming Language :: Python :: 3
Classifier: License :: Other/Proprietary License
Classifier: Operating System :: OS Independent
Requires-Dist: logger-local >=0.0.11
Requires-Dist: requests >=2.26.0
Requires-Dist: python-sdk-local >=0.0.27
Requires-Dist: user-context-remote >=0.0.21
Requires-Dist: url-local >=0.0.37
Requires-Dist: profile-local >=0.0.35
Requires-Dist: user-external-local >=0.0.32
